ch_requester/__init__.py
ch_requester/nc_requester.py
ch_requester/url_requester.py
CHRequester-0.0.1.dist-info/LICENSE
CHRequester-0.0.1.dist-info/METADATA
CHRequester-0.0.1.dist-info/WHEEL
CHRequester-0.0.1.dist-info/top_level.txt
CHRequester-0.0.1.dist-info/RECORD
