Metadata-Version: 2.1
Name: CHRequester
Version: 0.0.1
Summary: Cryptohack URL/NetCat request maker.
Home-page: https://github.com/maxime-peim/cryptohack-requester
Author: Maxime Peim
Author-email: maxime.peim@gmail.com
License: UNKNOWN
Project-URL: Bug Tracker, https://github.com/maxime-peim/cryptohack-requester/issues
Platform: UNKNOWN
Classifier: Programming Language :: Python :: 3
Classifier: License :: OSI Approved :: MIT License
Classifier: Operating System :: OS Independent
License-File: LICENSE
Requires-Dist: requests (>=2.26)
Requires-Dist: pwntools (>=4.6.0)
